cmprsk/__init__.py
cmprsk/cmprsk.py
cmprsk/rpy_utils.py
cmprsk/utils.py
cmprsk/tests/__init__.py
cmprsk/tests/test_cmprsk.py
cmprsk/tests/test_rpy_utils.py
cmprsk/tests/test_utils.py
cmprsk-1.1.1.dist-info/LICENSE
cmprsk-1.1.1.dist-info/METADATA
cmprsk-1.1.1.dist-info/WHEEL
cmprsk-1.1.1.dist-info/top_level.txt
cmprsk-1.1.1.dist-info/RECORD
