Metadata-Version: 2.1
Name: cmprsk
Version: 1.1.1
Summary: A python wrapper around cmprsk R package
Home-page: https://github.com/OmriTreidel/cmprsk
Author: Omri Treidel
Author-email: treidel2@gmail.com
Keywords: competing risks,survival analysis
Classifier: Programming Language :: Python :: 3
Classifier: License :: OSI Approved :: GNU General Public License v3 or later (GPLv3+)
Classifier: Operating System :: OS Independent
License-File: LICENSE
Requires-Dist: numpy
Requires-Dist: pandas
Requires-Dist: rpy2
Requires-Dist: scipy
